flask_themer.py
flask_themer-2.0.0.dist-info/LICENSE
flask_themer-2.0.0.dist-info/METADATA
flask_themer-2.0.0.dist-info/WHEEL
flask_themer-2.0.0.dist-info/top_level.txt
flask_themer-2.0.0.dist-info/RECORD
