Metadata-Version: 2.1
Name: flask-themer
Version: 2.0.0
Summary: Simple theme mechanism for Flask
Home-page: https://github.com/tktech/flask-themer
Author: Tyler Kennedy
Author-email: tk@tkte.ch
License: UNKNOWN
Keywords: flask,themes,jinja2
Platform: UNKNOWN
Classifier: Programming Language :: Python :: 3
Classifier: License :: OSI Approved :: MIT License
Classifier: Operating System :: OS Independent
Requires-Python: >=3.8
Requires-Dist: flask
